autoeda/__init__.py
autoeda/core.py
autoeda_sujay-0.1.0.dist-info/METADATA
autoeda_sujay-0.1.0.dist-info/WHEEL
autoeda_sujay-0.1.0.dist-info/top_level.txt
autoeda_sujay-0.1.0.dist-info/RECORD
